pycast_s2s/__init__.py
pycast_s2s/_version.py
pycast_s2s/PyCast_S2S.egg-info/PKG-INFO
pycast_s2s/PyCast_S2S.egg-info/SOURCES.txt
pycast_s2s/PyCast_S2S.egg-info/dependency_links.txt
pycast_s2s/PyCast_S2S.egg-info/entry_points.txt
pycast_s2s/PyCast_S2S.egg-info/requires.txt
pycast_s2s/PyCast_S2S.egg-info/top_level.txt
pycast_s2s/cli/aggregate.py
pycast_s2s/cli/process_global_forecasts.py
pycast_s2s/cli/process_regional_forecasts.py
pycast_s2s/cli/process_regional_reference.py
pycast_s2s/cli/run_bc.py
pycast_s2s/cli/run_bcsd.py
pycast_s2s/cli/run_eval.py
pycast_s2s/modules/__init__.py
pycast_s2s/modules/aggregation_modules.py
pycast_s2s/modules/bc_module.py
pycast_s2s/modules/cluster_modules.py
pycast_s2s/modules/global_processing_modules.py
pycast_s2s/modules/logger_setup.py
pycast_s2s/modules/regional_processing_modules.py
pycast_s2s/modules/utils.py
pycast_s2s/old_stuff/bc_module_v2.py
pycast_s2s/old_stuff/bc_module_v3.py
pycast_s2s/old_stuff/delayed_module.py
pycast_s2s/old_stuff/io_module.py
pycast_s2s/old_stuff/run_bcsd_v2.py
pycast_s2s/old_stuff/set_metadata.py
pycast_s2s/old_stuff/setup_domain.py
pycast_s2s/old_stuff/setup_domain_func.py
pycast_s2s/old_stuff/setup_new_domain.py
pycast_s2s/scripts/register_kernel.py
pycast_s2s/shapefiles/SaWaM_Forecast_Domains_Chira.dbf
pycast_s2s/shapefiles/SaWaM_Forecast_Domains_Chira.shp
pycast_s2s/shapefiles/SaWaM_Forecast_Domains_Chira.shx
pycast_s2s/shapefiles/SaWaM_Forecast_Domains_Khuzestan.dbf
pycast_s2s/shapefiles/SaWaM_Forecast_Domains_Khuzestan.shp
pycast_s2s/shapefiles/SaWaM_Forecast_Domains_Khuzestan.shx
pycast_s2s/shapefiles/SaWaM_Forecast_Domains_SF_Basin.dbf
pycast_s2s/shapefiles/SaWaM_Forecast_Domains_SF_Basin.shp
pycast_s2s/shapefiles/SaWaM_Forecast_Domains_SF_Basin.shx
pycast_s2s/shapefiles/SaWaM_Forecast_Domains_TABN.dbf
pycast_s2s/shapefiles/SaWaM_Forecast_Domains_TABN.shp
pycast_s2s/shapefiles/SaWaM_Forecast_Domains_TABN.shx
pycast_s2s-0.5.3.post1.dist-info/LICENSE
pycast_s2s-0.5.3.post1.dist-info/METADATA
pycast_s2s-0.5.3.post1.dist-info/WHEEL
pycast_s2s-0.5.3.post1.dist-info/entry_points.txt
pycast_s2s-0.5.3.post1.dist-info/top_level.txt
pycast_s2s-0.5.3.post1.dist-info/RECORD
