Metadata-Version: 2.2
Name: pycast_s2s
Version: 0.5.3.post1
Summary: Python-based tools for post-processing seasonal climate forecasts
Author-email: Christian Chwala <Christian.Chwala@kit.edu>, Benjamin Fersch <Benjamin.Fersch@kit.edu>, Christof Lorenz <Christof.Lorenz@kit.edu>, Windmanagda Sawadogo <windmanagda.sawadogo@geo.uni-augsburg.de>, Jan Weber <jan.weber@kit.edu>, Rebecca Wiegels <rebecca.wiegels@kit.edu>
Project-URL: Homepage, https://codebase.helmholtz.cloud/kit-seasonal-forecast-task-force/pycast-s2s
Project-URL: Bug Tracker, https://codebase.helmholtz.cloud/kit-seasonal-forecast-task-force/pycast-s2s/-/issues
Classifier: Programming Language :: Python :: 3
Classifier: License :: OSI Approved :: MIT License
Classifier: Operating System :: OS Independent
Requires-Python: >=3.8
License-File: LICENSE
Requires-Dist: pandas
Requires-Dist: dask[complete]
Requires-Dist: dask-jobqueue
Requires-Dist: xarray
Requires-Dist: numpy
Requires-Dist: netCDF4
Requires-Dist: scipy
Requires-Dist: surpyval
Requires-Dist: formulaic
Requires-Dist: s3fs
Requires-Dist: zarr
Requires-Dist: rechunker
Requires-Dist: tqdm
Requires-Dist: cdo
Requires-Dist: eccodes
Requires-Dist: cfgrib
Requires-Dist: python-dotenv
Requires-Dist: pytest
Requires-Dist: pre-commit
Requires-Dist: sphinx
Requires-Dist: sphinx-rtd-theme
Requires-Dist: ipykernel
Requires-Dist: jupyterlab
